deepchain/__init__.py
deepchain/scorer.py
deepchain-0.0.1.dist-info/LICENSE
deepchain-0.0.1.dist-info/METADATA
deepchain-0.0.1.dist-info/WHEEL
deepchain-0.0.1.dist-info/top_level.txt
deepchain-0.0.1.dist-info/RECORD
