Metadata-Version: 2.1
Name: deepchain
Version: 0.0.1
Summary: Define a personnal scorer for the user of DeepChain.bio
Home-page: UNKNOWN
Author: UNKNOWN
Author-email: UNKNOWN
License: UNKNOWN
Platform: UNKNOWN
